teenypm/__init__.py
teenypm/teenypm.py
teenypm/plugins/github.py
teenypm/plugins/local.py
teenypm-0.1.8.dist-info/entry_points.txt
teenypm-0.1.8.dist-info/LICENSE
teenypm-0.1.8.dist-info/WHEEL
teenypm-0.1.8.dist-info/METADATA
teenypm-0.1.8.dist-info/RECORD
