Metadata-Version: 2.1
Name: teenypm
Version: 0.1.8
Summary: A teeny CLI project manager
Home-page: https://github.com/joeyspacerocks/pm
License: UNKNOWN
Author: Joe Trewin
Author-email: joe.trewin@gmail.com
Classifier: License :: OSI Approved :: Apache Software License
Requires-Dist: rich
Requires-Dist: dateparser
Requires-Dist: humanize
Requires-Dist: requests
